geoffrey_clonedigger-0.0.1.dist-info/DESCRIPTION.rst
geoffrey_clonedigger-0.0.1.dist-info/RECORD
geoffrey_clonedigger-0.0.1.dist-info/WHEEL
geoffrey_clonedigger-0.0.1.dist-info/top_level.txt
geoffrey_clonedigger-0.0.1.dist-info/metadata.json
geoffrey_clonedigger-0.0.1.dist-info/METADATA
geoffreyplugins/__init__.py
geoffreyplugins/clonedigger.py
geoffreyplugins/clonedigger/main.js
geoffreyplugins/clonedigger/assets/.gitkeep
