Metadata-Version: 2.0
Name: geoffrey-clonedigger
Version: 0.0.1
Summary: tool for finding software clones
Home-page: https://github.com/GeoffreyCI/geoffrey-clonedigger
Author: Miguel Reguero Bejar
Author-email: mreguerob0@gmail.com
License: UNKNOWN
Platform: UNKNOWN
